reworkd_platform/__init__.py
reworkd_platform/__main__.py
reworkd_platform/conftest.py
reworkd_platform/constants.py
reworkd_platform/logging.py
reworkd_platform/settings.py
reworkd_platform/timer.py
reworkd_platform/db/__init__.py
reworkd_platform/db/base.py
reworkd_platform/db/dependencies.py
reworkd_platform/db/meta.py
reworkd_platform/db/utils.py
reworkd_platform/db/crud/__init__.py
reworkd_platform/db/crud/agent.py
reworkd_platform/db/crud/base.py
reworkd_platform/db/crud/oauth.py
reworkd_platform/db/crud/organization.py
reworkd_platform/db/crud/user.py
reworkd_platform/db/models/__init__.py
reworkd_platform/db/models/agent.py
reworkd_platform/db/models/auth.py
reworkd_platform/db/models/user.py
reworkd_platform/schemas/__init__.py
reworkd_platform/schemas/agent.py
reworkd_platform/schemas/user.py
reworkd_platform/services/__init__.py
reworkd_platform/services/anthropic.py
reworkd_platform/services/oauth_installers.py
reworkd_platform/services/security.py
reworkd_platform/services/ssl.py
reworkd_platform/services/aws/__init__.py
reworkd_platform/services/aws/s3.py
reworkd_platform/services/pinecone/__init__.py
reworkd_platform/services/pinecone/lifetime.py
reworkd_platform/services/pinecone/pinecone.py
reworkd_platform/services/tokenizer/__init__.py
reworkd_platform/services/tokenizer/dependencies.py
reworkd_platform/services/tokenizer/lifetime.py
reworkd_platform/services/tokenizer/token_service.py
reworkd_platform/tests/__init__.py
reworkd_platform/tests/test_dependancies.py
reworkd_platform/tests/test_helpers.py
reworkd_platform/tests/test_oauth_installers.py
reworkd_platform/tests/test_reworkd_platform.py
reworkd_platform/tests/test_s3.py
reworkd_platform/tests/test_schemas.py
reworkd_platform/tests/test_security.py
reworkd_platform/tests/test_settings.py
reworkd_platform/tests/test_token_service.py
reworkd_platform/web/__init__.py
reworkd_platform/web/application.py
reworkd_platform/web/lifetime.py
reworkd_platform/web/api/__init__.py
reworkd_platform-0.1.0.dist-info/METADATA
reworkd_platform-0.1.0.dist-info/WHEEL
reworkd_platform-0.1.0.dist-info/entry_points.txt
reworkd_platform-0.1.0.dist-info/top_level.txt
reworkd_platform-0.1.0.dist-info/RECORD
